<?xml version="1.0" encoding="UTF-8" standalone="yes"?>
<Spase xmlns:xsi="http://www.w3.org/2001/XMLSchema-instance" xmlns="http://www.spase-group.org/data/schema" xsi:schemaLocation="http://www.spase-group.org/data/schema http://www.spase-group.org/data/schema/spase-2_2_2.xsd">
   <Version>2.2.2</Version>
   <Observatory>
      <ResourceID>spase://SMWG/Observatory/Ground/Davis</ResourceID>
      <ResourceHeader>
         <ResourceName>Davis</ResourceName>
         <AlternateName>Observatory Station Code: DVS</AlternateName>
         <ReleaseDate>2018-05-30T12:34:56.789</ReleaseDate>
         <Description>The Davis geophysical observatory.</Description>
         <Acknowledgement>Please acknowledge:  Antarctic Division, Tasmania, Australia</Acknowledgement>
         <Contact>
            <PersonID>spase://SMWG/Person/Peter.Hopgood</PersonID>
            <Role>GeneralContact</Role>
            <Role>DataProducer</Role>
         </Contact>
         <Contact>
            <PersonID>spase://SMWG/Person/Gary.Burns</PersonID>
            <Role>GeneralContact</Role>
            <Role>DataProducer</Role>
         </Contact>
         <Contact>
            <PersonID>spase://SMWG/Person/Lee.Frost.Bargatze</PersonID>
            <Role>MetadataContact</Role>
         </Contact>
		 <InformationURL>
			  <Name>Geoscience Australia: Minute Values Request Form</Name> 
			  <URL>http://www.ga.gov.au/oracle/geomag/minute_ftp.jsp</URL> 
			  <Description>Requestion form for 1 minute resolution magnetometer data. 
			  Links to additional information also available.</Description> 
		  </InformationURL>
         <PriorID>spase://SMWG/Observatory/WDC/Davis</PriorID>
      </ResourceHeader>
      <ObservatoryGroupID>spase://SMWG/Observatory/Ground/WDC</ObservatoryGroupID>
	  <ObservatoryGroupID>spase://SMWG/Observatory/Ground/GA</ObservatoryGroupID>
      <Location>
         <ObservatoryRegion>Earth.Surface</ObservatoryRegion>
         <CoordinateSystemName>GEO</CoordinateSystemName>
         <Latitude>-68.583</Latitude>
         <Longitude>77.967</Longitude>
      </Location>
      <OperatingSpan>
         <StartDate>1988-02-01T00:00:00.000</StartDate>
      </OperatingSpan>
   </Observatory>
</Spase>
