<?xml version="1.0" encoding="UTF-8" standalone="yes"?>
<Spase xmlns:xsi="http://www.w3.org/2001/XMLSchema-instance" xmlns="http://www.spase-group.org/data/schema" xsi:schemaLocation="http://www.spase-group.org/data/schema http://www.spase-group.org/data/schema/spase-2_2_8.xsd">
   <Version>2.2.8</Version>
   <Observatory>
      <ResourceID>spase://SMWG/Observatory/Ground/Paamiut</ResourceID>
      <ResourceHeader>
         <ResourceName>Paamiut Geophysical Observatory</ResourceName>
   <AlternateName>Observatory Station Code: FHB</AlternateName>
         <AlternateName>Frederikshap Vector Magnetic Field 1.0 min Data Geophysical Observatory</AlternateName>
         <ReleaseDate>2019-05-05T12:34:56Z</ReleaseDate>
         <Description>Paamiut (FHB) Geophysical Observatory</Description>
         <Acknowledgement>Please acknowledge: DTU Space, Denmark</Acknowledgement>
         <Contact>
            <PersonID>spase://SMWG/Person/Claudia.Stolle</PersonID>
            <Role>PrincipalInvestigator</Role>
</Contact>
         <Contact>
            <PersonID>spase://SMWG/Person/Juergen.Matzka</PersonID>
            <Role>PrincipalInvestigator</Role>
</Contact>
         <Contact>
            <PersonID>spase://SMWG/Person/Lee.Frost.Bargatze</PersonID>
            <Role>MetadataContact</Role>
</Contact>
         <InformationURL>
            <Name>THEMIS Fluxgate Ground-based Magnetometer (GMAG) Web Site</Name>
            <URL>http://themis.ssl.berkeley.edu/instrument_gmags.shtml</URL>
            <Description>THEMIS makes data available from GMAG stations in the United States, Canada, Denmark, Greenland, Norway, Sweden, Iceland, and Russia, and Antarctica.</Description>
</InformationURL>
   <InformationURL>
     <Name>Technical University of Danmark</Name>
     <URL>https://www.space.dtu.dk/English/Research/Scientific_data_and_models/Magnetic_Ground_Stations.aspx</URL>
     <Description>Introduction to the DTU magnetometer data, plots, maps, etc.</Description>
</InformationURL>
</ResourceHeader>
   <ObservatoryGroupID>spase://SMWG/Observatory/Ground/DTU</ObservatoryGroupID>
   <ObservatoryGroupID>spase://SMWG/Observatory/Ground/TGO</ObservatoryGroupID>
   <ObservatoryGroupID>spase://SMWG/Observatory/Ground/GMAG</ObservatoryGroupID>
      <Location>
         <ObservatoryRegion>Earth.Surface</ObservatoryRegion>
         <CoordinateSystemName>GEO</CoordinateSystemName>
         <Latitude>62.0</Latitude>
         <Longitude>310.32</Longitude>
         <Elevation>1.0</Elevation>
</Location>
      <OperatingSpan>
         <StartDate>1981-11-01T00:00:00.000</StartDate>
   <Note>Exact start date is unclear.</Note>
</OperatingSpan>
</Observatory>
</Spase>
