<?xml version="1.0" encoding="UTF-8" standalone="yes"?>
<Spase xmlns:xsi="http://www.w3.org/2001/XMLSchema-instance" xmlns="http://www.spase-group.org/data/schema" xsi:schemaLocation="http://www.spase-group.org/data/schema http://www.spase-group.org/data/schema/spase-2_2_2.xsd">
   <Version>2.2.2</Version>
   <Observatory>
      <ResourceID>spase://SMWG/Observatory/Ground/Parc.St.Maur</ResourceID>
      <ResourceHeader>
         <ResourceName>Parc St Maur</ResourceName>
         <AlternateName>Observatory Station Code: PSM</AlternateName>
         <ReleaseDate>2018-09-06T12:34:56.789</ReleaseDate>
         <Description>The Parc St Maur geophysical observatory.</Description>
         <Acknowledgement>Please acknowledge:  Parc St Maur Observatory Director</Acknowledgement>
         <Contact>
            <PersonID>spase://SMWG/Person/WDC/Director.Parc.St.Maur.Observatory</PersonID>
            <Role>GeneralContact</Role>
            <Role>DataProducer</Role>
         </Contact>
         <Contact>
            <PersonID>spase://SMWG/Person/Lee.Frost.Bargatze</PersonID>
            <Role>MetadataContact</Role>
         </Contact>
      </ResourceHeader>
      <ObservatoryGroupID>spase://SMWG/Observatory/Ground/WDC</ObservatoryGroupID>
	  <ObservatoryGroupID>spase://SMWG/Observatory/Ground/BCMT</ObservatoryGroupID>
      <Location>
         <ObservatoryRegion>Earth.Surface</ObservatoryRegion>
         <CoordinateSystemName>GEO</CoordinateSystemName>
         <Latitude>48.81</Latitude>
         <Longitude>2.49</Longitude>
		 <Elevation>50.0</Elevation>
      </Location>
      <OperatingSpan>
         <StartDate>1883-01-01T00:00:00.000</StartDate>
      </OperatingSpan>
   </Observatory>
</Spase>
