<?xml version="1.0" encoding="UTF-8" standalone="yes"?>
<Spase xmlns:xsi="http://www.w3.org/2001/XMLSchema-instance" xmlns="http://www.spase-group.org/data/schema" xsi:schemaLocation="http://www.spase-group.org/data/schema http://www.spase-group.org/data/schema/spase-2_2_8.xsd">
   <Version>2.2.8</Version>
   <Observatory>
      <ResourceID>spase://SMWG/Observatory/Ground/Sanikiluaq</ResourceID>
      <ResourceHeader>
         <ResourceName>Sanikiluaq Geophysical Observatory</ResourceName>
		 <AlternateName>Observatory Station Code: SNKQ</AlternateName>
         <ReleaseDate>2019-01-16T12:34:56.789</ReleaseDate>
         <Description>Sanikiluaq (SNKQ) Geophysical Observatory</Description>
         <Acknowledgement>Please acknowledge: University of Alberta</Acknowledgement>
         <Contact>
            <PersonID>spase://SMWG/Person/Ian.Mann</PersonID>
            <Role>PrincipalInvestigator</Role>
         </Contact>
         <Contact>
            <PersonID>spase://SMWG/Person/Lee.Frost.Bargatze</PersonID>
            <Role>MetadataContact</Role>
         </Contact>
         <InformationURL>
            <Name>THEMIS Fluxgate Ground-based Magnetometer (GMAG) Web Site</Name>
            <URL>http://themis.ssl.berkeley.edu/instrument_gmags.shtml</URL>
            <Description>THEMIS makes data available from GMAG stations in the United States, Canada, Denmark, Greenland, Norway, Sweden, Iceland, and Russia, and Antarctica.</Description>
         </InformationURL>
		 <InformationURL>
			<Name>Canadian Array for Realtime Investigations of Magnetic Activity Homepage</Name>
			<URL>http://www.carisma.ca</URL>
			<Description>Detailed information about the CARISMA Array.</Description>
		 </InformationURL>
         <PriorID>spase://SMWG/Observatory/THEMIS/Ground/CANMAG/SNKQ</PriorID>
      </ResourceHeader>
      <Location>
         <ObservatoryRegion>Earth.Surface</ObservatoryRegion>
         <CoordinateSystemName>GEO</CoordinateSystemName>
         <Latitude>56.5</Latitude>
         <Longitude>280.8</Longitude>
      </Location>
      <OperatingSpan>
         <StartDate>2007-07-09T00:00:00</StartDate>
      </OperatingSpan>
   </Observatory>
</Spase>
