<?xml version="1.0" encoding="UTF-8" standalone="yes"?>
<Spase xmlns:xsi="http://www.w3.org/2001/XMLSchema-instance" xmlns="http://www.spase-group.org/data/schema" xsi:schemaLocation="http://www.spase-group.org/data/schema http://www.spase-group.org/data/schema/spase-2_2_2.xsd">
   <Version>2.2.2</Version>
   <Person>
      <ResourceID>spase://SMWG/Person/Alexandre.Sursock</ResourceID>
      <ReleaseDate>2012-04-20T12:34:56.789</ReleaseDate>
      <PersonName>Alexandre Sursock</PersonName>
      <OrganizationName>National Center for Geophysical Research-CNRS</OrganizationName>
      <Address>The National Centre for Geophysical Research, P.O. Box 16-5432, Beirut 1100-2040, Lebanon</Address>
      <Email>geophys@cnrs.edu.lb</Email>
   </Person>
</Spase>
