<?xml version="1.0" encoding="UTF-8"?>
<Spase xmlns:xsi="http://www.w3.org/2001/XMLSchema-instance" xmlns="http://www.spase-group.org/data/schema" xsi:schemaLocation="http://www.spase-group.org/data/schema http://www.spase-group.org/data/schema/spase-2_2_0.xsd">
  <Version>2.2.0</Version>
  <Person>
    <ResourceID>spase://SMWG/Person/Howard.J.Singer</ResourceID>
    <PersonName>Dr. Howard J. Singer</PersonName>
    <OrganizationName>NOAA Space Weather Prediction Center</OrganizationName>
    <Address>Space Weather Prediction Center, W/NP9 325 Broadway, Boulder CO 80305</Address>
    <Email>Howard.Singer@noaa.gov</Email>
    <PhoneNumber>303-497-6959</PhoneNumber>
  </Person>
</Spase>
