<?xml version="1.0"?>
<Spase xmlns="http://www.spase-group.org/data/schema">
   <Version>2.0.1</Version>
   <Person>
      <ResourceID>spase://SMWG/Person/Lee.Frost.Bargatze</ResourceID>
      <ReleaseDate>2009-11-05T12:34:56.789</ReleaseDate>
      <PersonName>Lee Frost Bargatze</PersonName>
      <OrganizationName>Virtual Magnetospheric Observatory, UCLA</OrganizationName>
      <Address>Institute of Geophysics and Planetary Physics, University of California Los Angeles, 805 E Charles Young Drive, Los Angeles, CA 90095-1567</Address>
      <Email>lfb@igpp.ucla.edu</Email>
      <PhoneNumber>+1 613 837 7915</PhoneNumber>
   </Person>
</Spase>
