<?xml version="1.0" encoding="UTF-8"?>
<Spase xmlns:xsi="http://www.w3.org/2001/XMLSchema-instance" xmlns="http://www.spase-group.org/data/schema" xsi:schemaLocation="http://www.spase-group.org/data/schema  http://www.spase-group.org/data/schema/spase-2_2_1.xsd">
  <Version>2.2.1</Version>
  <Person>
    <ResourceID>spase://SMWG/Person/Toshihiko.Iyemori</ResourceID>
    <ReleaseDate>2011-12-23T20:37:00Z</ReleaseDate>
    <PersonName>Toshihiko.Iyemori</PersonName>
    <OrganizationName>WDC for Geomagnetism, Kyoto U.</OrganizationName>
    <Email>iyemori@kugi.kyoto-u.ac.jp</Email>
  </Person>
</Spase>
