<?xml version='1.0' encoding='UTF-8'?>
<Spase xmlns:xsi="http://www.w3.org/2001/XMLSchema-instance" xmlns="http://www.spase-group.org/data/schema" xsi:schemaLocation="https://www.spase-group.org/data/schema https://www.spase-group.org/data/schema/spase-2.7.1.xsd">
  <Version>2.7.1</Version>
  <Person>
    <ResourceID>spase://SMWG/Person/Yuri.Y.Shprits</ResourceID>
    <NamingAuthority>SMWG</NamingAuthority>
    <ResourceType>Person</ResourceType>
    <ReleaseDate>2010-03-01T00:00:00Z</ReleaseDate>
    <PersonName>Dr. Yuri Y. Shprits</PersonName>
    <OrganizationName>UCLA, Institute of Geophysics and Planetary Physics and Department of Atmospheric Sciences</OrganizationName>
    <Address>405 Hilgard Ave/7127 Math Sciences Bldg Los Angeles, California 90095-1565</Address>
    <Email>yshprits@atmos.ucla.edu</Email>
  </Person>
</Spase>
