<?xml version="1.0" encoding="UTF-8"?>
<Spase xmlns:xsi="http://www.w3.org/2001/XMLSchema-instance" xmlns="http://www.spase-group.org/data/schema" xsi:schemaLocation="http://www.spase-group.org/data/schema http://www.spase-group.org/data/schema/spase-1_2_0.xsd">
  <Version>1.2.0</Version>
  <Instrument>
    <ResourceID>spase://SMWG/instrument/1995-039A-02</ResourceID>
    <ResourceHeader>
      <ResourceName>Low and Energetic Charged Particle Composition and Anisotropy (SKA-2)</ResourceName>
      <ReleaseDate>2008-06-18T05:32:50Z</ReleaseDate>
      <Description>This instrument makes measurements of the solar wind ion fluxes and energy-angular distributions of H+ and He++ around the Sun direction with high time resolution.</Description>
      <Contact>
        <PersonID>spase://SMWG/Person/E.I.Morozova</PersonID>
        <Role>PrincipalInvestigator</Role>
      </Contact>
      <InformationURL>
        <Name>NSSDC's Master Catalog</Name>
        <URL>http://nssdc.gsfc.nasa.gov/database/MasterCatalog?sc=1995-039A&amp;ex=2</URL>
        <Description>Information about the Low and Energetic Charged Particle Composition and Anisotropy (SKA-2) experiment on the Interball Tail Probe mission.</Description>
      </InformationURL>
    </ResourceHeader>
    <InstrumentType>EnergeticParticleInstrument</InstrumentType>
    <InvestigationName>Low and Energetic Charged Particle Composition and Anisotropy (SKA-2) on Interball Tail Probe</InvestigationName>
    <ObservatoryID>spase://SMWG/Observatory/Interball-1</ObservatoryID>
  </Instrument>
</Spase>
