<?xml version="1.0" encoding="UTF-8"?>
<Spase xmlns:xsi="http://www.w3.org/2001/XMLSchema-instance" xmlns="http://www.spase-group.org/data/schema" xsi:schemaLocation="http://www.spase-group.org/data/schema http://www.spase-group.org/data/schema/spase-2_0_0.xsd">
  <Version>2.0.0</Version>
  <Instrument>
    <ResourceID>spase://SMWG/Instrument/Magion-4/VDPS</ResourceID>
    <ResourceHeader>
      <ResourceName>Plasma Flow Detector VDP-S</ResourceName>
      <ReleaseDate>2019-05-05T12:34:56Z</ReleaseDate>
      <Description>This instrument consists of four Faraday cup detectors, registering ions and electrons with energies above 170 eV. The detectors are oriented at +/- 45 degrees from the main axis of the spacecraft, and have an angular aperture of 100 degrees. The maximum frequencies used are 1, 2, 4, and 8 Hz (depending on the telemetry mode).</Description>
      <Contact>
        <PersonID>spase://SMWG/Person/Georgy.Zastenker</PersonID>
        <Role>PrincipalInvestigator</Role>
</Contact>
      <InformationURL>
        <Name>NSSDC's Master Catalog</Name>
        <URL>https://nssdc.gsfc.nasa.gov/nmc/experiment/display.action?id=1995-039F&amp;ex=8</URL>
        <Description>Information about the Plasma Flow Detector VDP-S experiment on the Interball S2-X mission.</Description>
</InformationURL>
</ResourceHeader>
    <InstrumentType>FaradayCup</InstrumentType>
    <InvestigationName>Plasma Flow Detector VDP-S on Interball S2-X</InvestigationName>
    <ObservatoryID>spase://SMWG/Observatory/Magion-4</ObservatoryID>
</Instrument>
</Spase>
