<?xml version="1.0" encoding="UTF-8" standalone="yes"?>
<Spase xmlns="http://www.spase-group.org/data/schema">
  <Version>1.2.0</Version>
  <Instrument>
    <ResourceID>spase://SMWG/Instrument/WDC/Bereznyaki/Magnetometer</ResourceID>
    <ResourceHeader>
      <ResourceName>Bereznyaki Ground Magnetic Field Instrument</ResourceName>
      <AlternateName/>
      <ReleaseDate>2008-08-21T16:37:57Z</ReleaseDate>
      <ExpirationDate>2099-12-31T23:59:59.999</ExpirationDate>
      <Description>The magnetic field instrument at the Bereznyaki ground station</Description>
      <Acknowledgement>Arti Geophysical Observatory, Institute of Geophysics,, Urals Branch of Russian Academy of Sciences</Acknowledgement>
      <Contact>
        <PersonID>spase://SMWG/Person/Oleg.Kusonski</PersonID>
        <Role>GeneralContact</Role>
      </Contact>
      <Contact>
        <PersonID>spase://SMWG/Person/Lee.Frost.Bargatze</PersonID>
        <Role>MetadataContact</Role>
      </Contact>
      <InformationURL>
        <Name>The Bereznyaki magnetometer web site</Name>
        <URL>HARVEST</URL>
        <Description>The Bereznyaki magnetometer web site</Description>
      </InformationURL>
      <PriorID>spase://VMO/Instrument/WDC/Bereznyaki/Magnetometer</PriorID>
    </ResourceHeader>
    <InstrumentType>Magnetometer</InstrumentType>
    <InvestigationName>None Identified</InvestigationName>
    <ObservatoryID>spase://SMWG/Observatory/WDC/Bereznyaki</ObservatoryID>
    <Caveats/>
  </Instrument>
</Spase>
